cambrinary/Conf.py
cambrinary/__init__.py
cambrinary/cambrinary.py
cambrinary/color_const.py
cambrinary/conf.json
cambrinary/country_const.py
cambrinary/log.py
cambrinary/requirements.in
cambrinary/requirements.txt
cambrinary/type.py
cambrinary-0.1.3.dist-info/entry_points.txt
cambrinary-0.1.3.dist-info/LICENSE
cambrinary-0.1.3.dist-info/WHEEL
cambrinary-0.1.3.dist-info/METADATA
cambrinary-0.1.3.dist-info/RECORD
