Metadata-Version: 2.1
Name: cambrinary
Version: 0.1.3
Summary: A Linux terminal online dictionary, based on `Cambridge Dictionary <https://dictionary.cambridge.org>`_
Home-page: https://github.com/xueyuanl/cambrinary
License: UNKNOWN
Keywords: dictionary cambridge
Author: xueyuanl
Author-email: p.xueyuanl@gmail.com
Requires-Python: >=3.5.3
Classifier: License :: OSI Approved :: GNU General Public License v3 or later (GPLv3+)
Classifier: Environment :: Console
Requires-Dist: aiohttp
Requires-Dist: beautifulsoup4
Requires-Dist: flit ; extra == "publish"
Provides-Extra: publish
